dsbix/__init__.py
dsbix-0.1.dist-info/METADATA
dsbix-0.1.dist-info/WHEEL
dsbix-0.1.dist-info/top_level.txt
dsbix-0.1.dist-info/RECORD
