Metadata-Version: 2.1
Name: dsbix
Version: 0.1
Summary: API für DSBMobile via tesseract.
Home-page: https://github.com/zfqtim/dsbix
Author: veoh
Author-email: zfq@tuta.io
Classifier: Programming Language :: Python :: 3
Classifier: License :: OSI Approved :: GNU General Public License v3 (GPLv3)
Classifier: Operating System :: OS Independent
Requires-Python: >=3.5
